fastapi_tusd/__init__.py
fastapi_tusd/cli.py
fastapi_tusd/filestore.py
fastapi_tusd/tusd.py
fastapi_tusd-0.100.2.dist-info/AUTHORS.md
fastapi_tusd-0.100.2.dist-info/LICENSE
fastapi_tusd-0.100.2.dist-info/METADATA
fastapi_tusd-0.100.2.dist-info/WHEEL
fastapi_tusd-0.100.2.dist-info/top_level.txt
fastapi_tusd-0.100.2.dist-info/RECORD
