Metadata-Version: 2.1
Name: fastapi-tusd
Version: 0.100.2
Summary: FastAPI extention implementing the tus server
Home-page: https://github.com/liviaerxin/fastapi-tusd
Author: Frank
Author-email: 1yue8haogaoqi@gmail.com
License: MIT license
Keywords: fastapi-tusd
Classifier: Topic :: Software Development :: Libraries :: Python Modules
Classifier: Topic :: Software Development :: Libraries
Classifier: Topic :: Software Development
Classifier: Framework :: FastAPI
Classifier: Framework :: Pydantic
Classifier: Programming Language :: Python :: 3 :: Only
Classifier: Programming Language :: Python :: 3.7
Classifier: Programming Language :: Python :: 3.8
Classifier: Programming Language :: Python :: 3.9
Classifier: Programming Language :: Python :: 3.10
Classifier: Programming Language :: Python :: 3.11
Classifier: Topic :: Internet :: WWW/HTTP :: HTTP Servers
Classifier: Topic :: Internet :: WWW/HTTP
Requires-Python: >=3.7
License-File: LICENSE
License-File: AUTHORS.md
Requires-Dist: fastapi >=0.100.0
Requires-Dist: filelock
Provides-Extra: dev
Requires-Dist: uvicorn ; extra == 'dev'
Provides-Extra: format
Requires-Dist: black ; extra == 'format'
Provides-Extra: test
Requires-Dist: pytest >=3 ; extra == 'test'
Requires-Dist: pytest-cov ; extra == 'test'
